rox_septentrio/__init__.py
rox_septentrio/__main__.py
rox_septentrio/config.py
rox_septentrio/converters.py
rox_septentrio/gps_node_ip.py
rox_septentrio/gps_node_serial.py
rox_septentrio/mock.py
rox_septentrio/nmea.py
rox_septentrio/py.typed
rox_septentrio/runners.py
rox_septentrio-1.0.1.dist-info/LICENCE
rox_septentrio-1.0.1.dist-info/METADATA
rox_septentrio-1.0.1.dist-info/WHEEL
rox_septentrio-1.0.1.dist-info/entry_points.txt
rox_septentrio-1.0.1.dist-info/top_level.txt
rox_septentrio-1.0.1.dist-info/RECORD
