Metadata-Version: 2.1
Name: rox-septentrio
Version: 1.0.1
Summary: Driver for Septentrio GPS, posting messages to mqtt
Author-email: Jev Kuznetsov <jev@roxautomation.com>
License: MIT
Project-URL: Homepage, https://gitlab.com/roxautomation/components/septentrio-gps
Classifier: Development Status :: 3 - Alpha
Classifier: Intended Audience :: Developers
Classifier: Operating System :: OS Independent
Classifier: Programming Language :: Python
Classifier: Programming Language :: Python :: 3.10
Classifier: Topic :: Software Development :: Libraries :: Python Modules
Classifier: Typing :: Typed
Requires-Python: >=3.10
License-File: LICENCE
Requires-Dist: paho-mqtt
Requires-Dist: click
Requires-Dist: coloredlogs
Requires-Dist: orjson
Requires-Dist: pydantic-settings
Requires-Dist: pydantic
Requires-Dist: pymap3d
Requires-Dist: pynmea2
Requires-Dist: pyserial
